LICENSE
MANIFEST.in
README.rst
setup.cfg
setup.py
test/test_evalution.py
test/test_folder.py
test/test_nn.py
test/test_transforms.py
test/test_utils.py
torchcv/__init__.py
torchcv/utils.py
torchcv.egg-info/PKG-INFO
torchcv.egg-info/SOURCES.txt
torchcv.egg-info/dependency_links.txt
torchcv.egg-info/requires.txt
torchcv.egg-info/top_level.txt
torchcv.egg-info/zip-safe
torchcv/archs/__init__.py
torchcv/archs/cgan.py
torchcv/archs/create_model.py
torchcv/archs/cvae.py
torchcv/archs/cvaegan.py
torchcv/archs/dcgan.py
torchcv/archs/vae.py
torchcv/archs/DCGAN/DCGAN.py
torchcv/archs/DCGAN/__init__.py
torchcv/archs/DCGAN/run_DCGAN.py
torchcv/archs/GAN/GAN.py
torchcv/archs/GAN/__init__.py
torchcv/archs/GAN/run_GAN.py
torchcv/archs/ImprovedGAN/ImprovedGAN.py
torchcv/archs/ImprovedGAN/__init__.py
torchcv/archs/ImprovedGAN/run_ImprovedGAN.py
torchcv/archs/InfoGAN/InfoGAN.py
torchcv/archs/InfoGAN/__init__.py
torchcv/archs/InfoGAN/run_InfoGAN.py
torchcv/archs/LAPGAN/LAPGAN.py
torchcv/archs/LAPGAN/__init__.py
torchcv/archs/LAPGAN/run_LAPGAN.py
torchcv/archs/tests/__init__.py
torchcv/archs/tests/test_GANs.py
torchcv/convertdata/__init__.py
torchcv/convertdata/city.py
torchcv/convertdata/convert_tf_pytorch.py
torchcv/convertdata/genMaskAndImg.py
torchcv/convertdata/genMaskAndImglst.py
torchcv/convertdata/h5tool.py
torchcv/data/__init__.py
torchcv/data/base.py
torchcv/data/cityscapes.py
torchcv/data/cocoinstance.py
torchcv/data/image_folder.py
torchcv/datasets/__init__.py
torchcv/datasets/cifar.py
torchcv/datasets/coco.py
torchcv/datasets/fakedata.py
torchcv/datasets/folder.py
torchcv/datasets/lsun.py
torchcv/datasets/mnist.py
torchcv/datasets/multifolder.py
torchcv/datasets/omniglot.py
torchcv/datasets/phototour.py
torchcv/datasets/semeion.py
torchcv/datasets/stl10.py
torchcv/datasets/svhn.py
torchcv/datasets/utils.py
torchcv/evaluation/__init__.py
torchcv/evaluation/fid_inception.py
torchcv/evaluation/fid_score.py
torchcv/evaluation/inception_score.py
torchcv/image/__init__.py
torchcv/image/det.py
torchcv/image/detection.py
torchcv/image/image.py
torchcv/image/preprocess.py
torchcv/loss/__init__.py
torchcv/loss/vggloss.py
torchcv/models/__init__.py
