Metadata-Version: 1.0
Name: torchcv
Version: 0.0.2
Summary: image and video datasets and models for torch deep learning
Home-page: https://github.com/aaronleong/vision-tools
Author: liangshihua
Author-email: mc2liang@gmail.com
License: BSD
Platform: UNKNOWN
